mirage_linemode/__init__.py
mirage_linemode/__main__.py
mirage_linemode/args.py
mirage_linemode/config.py
mirage_linemode/mirage_linemode_ctrl.py
mirage_linemode/util.py
mirage_linemode/ranger_plugin/mirage_linemode.py
mirage_linemode/template/mirage_linemode_config.yml
mirage_linemode/template/mirage_linemode_theme.yml
mirage_linemode/theme/__init__.py
mirage_linemode/theme/core.py
mirage_linemode/theme/icon_width_list.py
mirage_linemode-0.1.1.dist-info/LICENSE.txt
mirage_linemode-0.1.1.dist-info/METADATA
mirage_linemode-0.1.1.dist-info/WHEEL
mirage_linemode-0.1.1.dist-info/entry_points.txt
mirage_linemode-0.1.1.dist-info/top_level.txt
mirage_linemode-0.1.1.dist-info/RECORD
