Metadata-Version: 2.1
Name: mirage-linemode
Version: 0.1.1
Summary: Customizable linemode plugin for ranger.
Home-page: https://github.com/hankei6km/mirage_linemode
Author: hankei6km
Author-email: hankei6km@gmail.com
License: MIT
Platform: UNKNOWN
Classifier: Development Status :: 2 - Pre-Alpha
Classifier: Topic :: Desktop Environment :: File Managers
Classifier: License :: OSI Approved :: MIT License
Classifier: Operating System :: POSIX :: Linux
Classifier: Environment :: Console
Classifier: Programming Language :: Python :: 2.7
Classifier: Programming Language :: Python :: 3.6
Requires-Dist: configparser
Requires-Dist: pyxdg
Requires-Dist: PyYAML
